autoroc_rupakbob/__init__.py
autoroc_rupakbob/autoroc.py
autoroc-0.0.1.dist-info/LICENSE
autoroc-0.0.1.dist-info/METADATA
autoroc-0.0.1.dist-info/WHEEL
autoroc-0.0.1.dist-info/top_level.txt
autoroc-0.0.1.dist-info/RECORD
